steffentools/__init__.py
steffentools/const.py
steffentools/dict_to_namedtuple.py
steffentools/dict_to_ntuple.py
steffentools-0.1.1.dist-info/LICENSE
steffentools-0.1.1.dist-info/METADATA
steffentools-0.1.1.dist-info/WHEEL
steffentools-0.1.1.dist-info/top_level.txt
steffentools-0.1.1.dist-info/RECORD
