Metadata-Version: 2.1
Name: steffentools
Version: 0.1.1
Summary: A collection of tools compiled for personal use.
Home-page: https://github.com/cmsteffen-code/steffentools
Author: CMSteffen
Author-email: cmsteffen@protonmail.com
License: MIT
Project-URL: Source Code, https://github.com/cmsteffen-code/steffentools
Project-URL: Documentation, https://steffentools.readthedocs.io/en/latest/
Keywords: steffentools tools library
Platform: UNKNOWN
Classifier: License :: OSI Approved :: MIT License
Classifier: Programming Language :: Python :: 3
Classifier: Programming Language :: Python :: 3.6
Classifier: Programming Language :: Python :: 3.7
